artificer_ai/__init__.py
artificer_ai/main.py
artificer_ai-0.0.1.dist-info/METADATA
artificer_ai-0.0.1.dist-info/WHEEL
artificer_ai-0.0.1.dist-info/RECORD
