Metadata-Version: 2.4
Name: artificer-ai
Version: 0.0.1
Summary: AI-powered tooling from the Artificer project.
Author-email: Scott Russell <me@scottrussell.net>
Requires-Python: >=3.9
